tinto.py
tinto_prueba/methods.py
tinto_prueba/probar.py
tinto_prueba-0.0.2.dist-info/METADATA
tinto_prueba-0.0.2.dist-info/WHEEL
tinto_prueba-0.0.2.dist-info/licenses/LICENSE
tinto_prueba-0.0.2.dist-info/RECORD
