Metadata-Version: 2.1
Name: tinto-prueba
Version: 0.0.2
Summary: TINTO package test
Project-URL: Homepage, https://github.com/oeg-upm/TINTO
Author-email: BorjaRei <borjareinoso@gmail.com>
License:                                  Apache License
License-File: LICENSE
Classifier: License :: OSI Approved :: MIT License
Classifier: Operating System :: OS Independent
Classifier: Programming Language :: Python :: 3
Requires-Python: >=3.8
